vaknl_conversion_model/__init__.py
vaknl_conversion_model/TrainingServing/__init__.py
vaknl_conversion_model-1.0.7.dist-info/LICENCE
vaknl_conversion_model-1.0.7.dist-info/METADATA
vaknl_conversion_model-1.0.7.dist-info/WHEEL
vaknl_conversion_model-1.0.7.dist-info/top_level.txt
vaknl_conversion_model-1.0.7.dist-info/RECORD
