Metadata-Version: 2.1
Name: vaknl-conversion-model
Version: 1.0.7
Summary: Conversion model package. Only contains training serving library for now. 
Home-page: https://github.com/vakantiesnl/vaknl-PyPi.git
Author: Merijn van Es
Author-email: merijn.vanes@vakanties.nl
License: UNKNOWN
Keywords: vaknl,pip
Platform: UNKNOWN
Requires-Python: >=2.7
Requires-Dist: tensorflow (>=2.1.0)
Requires-Dist: google
